{"dependencies":[{"name":"../math.js","loc":{"line":1,"column":25}},{"name":"./azimuthal.js","loc":{"line":2,"column":44}},{"name":"./index.js","loc":{"line":3,"column":23}}],"generated":{"js":"\"use strict\";\n\nObject.defineProperty(exports, \"__esModule\", {\n  value: true\n});\nexports.azimuthalEqualAreaRaw = undefined;\n\nexports.default = function () {\n  return (0, _index2.default)(azimuthalEqualAreaRaw).scale(124.75).clipAngle(180 - 1e-3);\n};\n\nvar _math = require(\"../math.js\");\n\nvar _azimuthal = require(\"./azimuthal.js\");\n\nvar _index = require(\"./index.js\");\n\nvar _index2 = _interopRequireDefault(_index);\n\nfunction _interopRequireDefault(obj) { return obj && obj.__esModule ? obj : { default: obj }; }\n\nvar azimuthalEqualAreaRaw = exports.azimuthalEqualAreaRaw = (0, _azimuthal.azimuthalRaw)(function (cxcy) {\n  return (0, _math.sqrt)(2 / (1 + cxcy));\n});\n\nazimuthalEqualAreaRaw.invert = (0, _azimuthal.azimuthalInvert)(function (z) {\n  return 2 * (0, _math.asin)(z / 2);\n});"},"hash":"0eaf7f9f6cd5caef7904bc7af42a3042"}