{"dependencies":[{"name":"./value.js","loc":{"line":1,"column":31}}],"generated":{"js":"\"use strict\";\n\nObject.defineProperty(exports, \"__esModule\", {\n  value: true\n});\nexports.default = piecewise;\n\nvar _value = require(\"./value.js\");\n\nvar _value2 = _interopRequireDefault(_value);\n\nfunction _interopRequireDefault(obj) { return obj && obj.__esModule ? obj : { default: obj }; }\n\nfunction piecewise(interpolate, values) {\n  if (values === undefined) values = interpolate, interpolate = _value2.default;\n  var i = 0,\n      n = values.length - 1,\n      v = values[0],\n      I = new Array(n < 0 ? 0 : n);\n  while (i < n) I[i] = interpolate(v, v = values[++i]);\n  return function (t) {\n    var i = Math.max(0, Math.min(n - 1, Math.floor(t *= n)));\n    return I[i](t - i);\n  };\n}"},"hash":"f5f3e8e24649cfa8fb4b636e35b7456a"}